async_openai/__init__.py
async_openai/client.py
async_openai/external_client.py
async_openai/loadbalancer.py
async_openai/manager.py
async_openai/meta.py
async_openai/routes.py
async_openai/version.py
async_openai/schemas/__init__.py
async_openai/schemas/chat.py
async_openai/schemas/completions.py
async_openai/schemas/edits.py
async_openai/schemas/embeddings.py
async_openai/schemas/images.py
async_openai/schemas/models.py
async_openai/schemas/external/__init__.py
async_openai/schemas/external/fireworks/__init__.py
async_openai/schemas/external/fireworks/chat.py
async_openai/schemas/external/together/__init__.py
async_openai/schemas/external/together/chat.py
async_openai/schemas/external/together/embeddings.py
async_openai/types/__init__.py
async_openai/types/context.py
async_openai/types/errors.py
async_openai/types/functions.py
async_openai/types/options.py
async_openai/types/pricing.yaml
async_openai/types/resources.py
async_openai/types/responses.py
async_openai/types/routes.py
async_openai/utils/__init__.py
async_openai/utils/config.py
async_openai/utils/embedding.py
async_openai/utils/external_config.py
async_openai/utils/fixjson.py
async_openai/utils/helpers.py
async_openai/utils/logs.py
async_openai/utils/resolvers.py
async_openai/utils/tokenization.py
async_openai/utils/presets/fireworks.yaml
async_openai/utils/presets/together.yaml
async_openai/utils/presets/together_proxy.yaml
async_openai-0.0.52.dist-info/LICENSE
async_openai-0.0.52.dist-info/METADATA
async_openai-0.0.52.dist-info/WHEEL
async_openai-0.0.52.dist-info/top_level.txt
async_openai-0.0.52.dist-info/RECORD
