Metadata-Version: 2.1
Name: async_openai
Version: 0.0.52
Summary: Unofficial Async Python client library for the OpenAI API
Home-page: https://github.com/GrowthEngineAI/async-openai
Author: Tri Songz
Author-email: ts@growthengineai.com
License: MIT Style
Classifier: Intended Audience :: Developers
Classifier: License :: OSI Approved :: MIT License
Classifier: Programming Language :: Python :: 3.7
Classifier: Topic :: Software Development :: Libraries
License-File: LICENSE
Requires-Dist: aiohttpx>=0.0.12
Requires-Dist: backoff
Requires-Dist: tiktoken
Requires-Dist: lazyops>=0.2.76
Requires-Dist: pydantic
Requires-Dist: jinja2
Requires-Dist: pyyaml
Provides-Extra: cache
Requires-Dist: kvdb; extra == "cache"
Provides-Extra: utils
Requires-Dist: numpy; extra == "utils"
Requires-Dist: scipy; extra == "utils"
